openbb_congress_gov/__init__.py
openbb_congress_gov/models/__init__.py
openbb_congress_gov/models/bill_info.py
openbb_congress_gov/models/bill_text.py
openbb_congress_gov/models/congress_bills.py
openbb_congress_gov/py.typed
openbb_congress_gov/router/__init__.py
openbb_congress_gov/router/congress_gov_router.py
openbb_congress_gov/utils/__init__.py
openbb_congress_gov/utils/constants.py
openbb_congress_gov/utils/helpers.py
openbb_congress_gov-1.0.0.dist-info/METADATA
openbb_congress_gov-1.0.0.dist-info/WHEEL
openbb_congress_gov-1.0.0.dist-info/entry_points.txt
openbb_congress_gov-1.0.0.dist-info/RECORD
