Metadata-Version: 2.4
Name: openbb-congress-gov
Version: 1.0.0
Summary: Congress.gov Provider Extension for the OpenBB Platform
Author: OpenBB Team
Author-email: hello@openbb.co
Requires-Python: >=3.9.21,<3.14
Classifier: Programming Language :: Python :: 3
Classifier: Programming Language :: Python :: 3.10
Classifier: Programming Language :: Python :: 3.11
Classifier: Programming Language :: Python :: 3.12
Classifier: Programming Language :: Python :: 3.13
Requires-Dist: openbb-core (>=1.5.0,<2.0.0)
